virocon/__init__.py
virocon/_fitting.py
virocon/_intersection.py
virocon/_nsphere.py
virocon/contours.py
virocon/dependencies.py
virocon/distributions.py
virocon/intervals.py
virocon/jointmodels.py
virocon/plotting.py
virocon/predefined.py
virocon/utils.py
virocon/variable_transform.py
virocon-2.4.0.dist-info/licenses/LICENSE
virocon-2.4.0.dist-info/METADATA
virocon-2.4.0.dist-info/WHEEL
virocon-2.4.0.dist-info/top_level.txt
virocon-2.4.0.dist-info/RECORD
