Metadata-Version: 2.4
Name: virocon
Version: 2.4.0
Summary: ViroCon is a software to compute environmental contours
Home-page: https://github.com/virocon-organization/virocon
Download-URL: https://github.com/virocon-organization/virocon/archive/2.4.0.tar.gz
Author: virocon team
Author-email: virocon@uni-bremen.de
Project-URL: Documentation, https://virocon.readthedocs.io
Project-URL: Source Code, https://github.com/virocon-organization/virocon
Classifier: Development Status :: 5 - Production/Stable
Classifier: Intended Audience :: Science/Research
Classifier: Topic :: Scientific/Engineering
Classifier: License :: OSI Approved :: MIT License
Classifier: Programming Language :: Python :: 3
Requires-Python: >=3.7
License-File: LICENSE
Requires-Dist: matplotlib>=2.2.0
Requires-Dist: networkx
Requires-Dist: numpy
Requires-Dist: pandas
Requires-Dist: scikit-learn
Requires-Dist: scipy
Provides-Extra: dev
Requires-Dist: Sphinx; extra == "dev"
Requires-Dist: ruff; extra == "dev"
Requires-Dist: pre-commit; extra == "dev"
Provides-Extra: test
Requires-Dist: pytest; extra == "test"
Requires-Dist: pytest-cov; extra == "test"
Requires-Dist: coverage; extra == "test"
Requires-Dist: coveralls; extra == "test"
Dynamic: author
Dynamic: author-email
Dynamic: classifier
Dynamic: description
Dynamic: download-url
Dynamic: home-page
Dynamic: license-file
Dynamic: project-url
Dynamic: provides-extra
Dynamic: requires-dist
Dynamic: requires-python
Dynamic: summary
